odoo/addons/purchase_backorder/README.rst
odoo/addons/purchase_backorder/__init__.py
odoo/addons/purchase_backorder/__manifest__.py
odoo/addons/purchase_backorder/i18n/de.po
odoo/addons/purchase_backorder/i18n/pt_BR.po
odoo/addons/purchase_backorder/i18n/purchase_backorder.pot
odoo/addons/purchase_backorder/i18n/sl.po
odoo/addons/purchase_backorder/models/__init__.py
odoo/addons/purchase_backorder/models/purchase.py
odoo/addons/purchase_backorder/readme/CONTRIBUTORS.rst
odoo/addons/purchase_backorder/readme/DESCRIPTION.rst
odoo/addons/purchase_backorder/readme/USAGE.rst
odoo/addons/purchase_backorder/report/po_backorder_report.xml
odoo/addons/purchase_backorder/security/ir.model.access.csv
odoo/addons/purchase_backorder/static/description/icon.png
odoo/addons/purchase_backorder/static/description/index.html
odoo/addons/purchase_backorder/views/po_backorder_view.xml
odoo/addons/purchase_backorder/views/purchase_view.xml
odoo/addons/purchase_backorder/wizard/__init__.py
odoo/addons/purchase_backorder/wizard/po_backorder_wizard.py
odoo/addons/purchase_backorder/wizard/po_backorder_wizard_view.xml
odoo14_addon_purchase_backorder-14.0.1.1.1.dist-info/METADATA
odoo14_addon_purchase_backorder-14.0.1.1.1.dist-info/WHEEL
odoo14_addon_purchase_backorder-14.0.1.1.1.dist-info/top_level.txt
odoo14_addon_purchase_backorder-14.0.1.1.1.dist-info/RECORD
